pysdmx/__extras_check.py
pysdmx/__init__.py
pysdmx/api/__init__.py
pysdmx/api/dc/__init__.py
pysdmx/api/dc/_api.py
pysdmx/api/dc/query/__init__.py
pysdmx/api/dc/query/_model.py
pysdmx/api/dc/query/_parsing_model.py
pysdmx/api/dc/query/_parsing_util.py
pysdmx/api/dc/query/_py_parser.py
pysdmx/api/dc/query/_sql_parser.py
pysdmx/api/dc/query/util.py
pysdmx/api/fmr/__init__.py
pysdmx/api/fmr/maintenance.py
pysdmx/api/gds/__init__.py
pysdmx/api/qb/__init__.py
pysdmx/api/qb/availability.py
pysdmx/api/qb/data.py
pysdmx/api/qb/gds.py
pysdmx/api/qb/refmeta.py
pysdmx/api/qb/registration.py
pysdmx/api/qb/schema.py
pysdmx/api/qb/service.py
pysdmx/api/qb/structure.py
pysdmx/api/qb/util.py
pysdmx/errors.py
pysdmx/io/__init__.py
pysdmx/io/csv/__csv_aux_reader.py
pysdmx/io/csv/__csv_aux_writer.py
pysdmx/io/csv/__init__.py
pysdmx/io/csv/sdmx10/__init__.py
pysdmx/io/csv/sdmx10/reader/__init__.py
pysdmx/io/csv/sdmx10/writer/__init__.py
pysdmx/io/csv/sdmx20/__init__.py
pysdmx/io/csv/sdmx20/reader/__init__.py
pysdmx/io/csv/sdmx20/writer/__init__.py
pysdmx/io/csv/sdmx21/__init__.py
pysdmx/io/csv/sdmx21/reader/__init__.py
pysdmx/io/csv/sdmx21/writer/__init__.py
pysdmx/io/format.py
pysdmx/io/input_processor.py
pysdmx/io/json/fusion/messages/__init__.py
pysdmx/io/json/fusion/messages/category.py
pysdmx/io/json/fusion/messages/code.py
pysdmx/io/json/fusion/messages/concept.py
pysdmx/io/json/fusion/messages/constraint.py
pysdmx/io/json/fusion/messages/core.py
pysdmx/io/json/fusion/messages/dataflow.py
pysdmx/io/json/fusion/messages/dsd.py
pysdmx/io/json/fusion/messages/map.py
pysdmx/io/json/fusion/messages/metadataflow.py
pysdmx/io/json/fusion/messages/mpa.py
pysdmx/io/json/fusion/messages/msd.py
pysdmx/io/json/fusion/messages/org.py
pysdmx/io/json/fusion/messages/pa.py
pysdmx/io/json/fusion/messages/report.py
pysdmx/io/json/fusion/messages/schema.py
pysdmx/io/json/fusion/messages/vtl.py
pysdmx/io/json/fusion/reader/__init__.py
pysdmx/io/json/gds/messages/__init__.py
pysdmx-1.10.1.dist-info/METADATA
pysdmx-1.10.1.dist-info/WHEEL
pysdmx-1.10.1.dist-info/licenses/LICENSE
pysdmx-1.10.1.dist-info/RECORD
