Metadata-Version: 2.4
Name: pysdmx
Version: 1.10.1
Summary: Your opinionated Python SDMX library
License: Apache-2.0
License-File: LICENSE
Keywords: sdmx,data discovery,data retrieval,metadata,fmr
Author: Xavier Sosnovsky
Author-email: <xavier.sosnovsky@bis.org>
Requires-Python: >=3.9
Classifier: Development Status :: 5 - Production/Stable
Classifier: Intended Audience :: Developers
Classifier: Intended Audience :: Science/Research
Classifier: License :: OSI Approved :: Apache Software License
Classifier: Typing :: Typed
Provides-Extra: all
Provides-Extra: data
Provides-Extra: dc
Provides-Extra: json
Provides-Extra: vtl
Provides-Extra: xml
Requires-Dist: httpx[http2] (>=0)
Requires-Dist: jsonschema (>=4.10) ; extra == "json"
Requires-Dist: lxml (>=5.2) ; extra == "all"
Requires-Dist: lxml (>=5.2) ; extra == "xml"
Requires-Dist: msgspec (>=0)
Requires-Dist: pandas (>=2.1.4) ; extra == "all"
Requires-Dist: pandas (>=2.1.4) ; extra == "data"
Requires-Dist: parsy (>=2.1)
Requires-Dist: python-dateutil (>=2.8.2) ; extra == "all"
Requires-Dist: python-dateutil (>=2.8.2) ; extra == "dc"
Requires-Dist: sdmxschemas (>=1.0.0) ; extra == "all"
Requires-Dist: sdmxschemas (>=1.0.0) ; extra == "json"
Requires-Dist: sdmxschemas (>=1.0.0) ; extra == "xml"
Requires-Dist: vtlengine (>=1.2,<2.0) ; extra == "all"
Requires-Dist: vtlengine (>=1.2,<2.0) ; extra == "vtl"
Requires-Dist: xmltodict (>=0.13) ; extra == "all"
Requires-Dist: xmltodict (>=0.13) ; extra == "xml"
Project-URL: Bug Tracker, https://bis-med-it.github.io/pysdmx/issues
Project-URL: Documentation, https://bis-med-it.github.io/pysdmx
Project-URL: Homepage, https://sdmx.io/tools/pysdmx
Project-URL: Repository, https://github.com/bis-med-it/pysdmx
